convertio/__init__.py
convertio/__version__.py
convertio/client.py
convertio/conversion.py
convertio/options.py
convertio/types.py
convertio-1.1.2.dist-info/LICENSE
convertio-1.1.2.dist-info/METADATA
convertio-1.1.2.dist-info/WHEEL
convertio-1.1.2.dist-info/top_level.txt
convertio-1.1.2.dist-info/RECORD
