Metadata-Version: 2.1
Name: convertio
Version: 1.1.2
Summary: An API wrapper for convertio.co
Home-page: https://github.com/PetitPotiron/python-convertio/
Author: PetitPotiron
License: GNU General Public License v3.0
Platform: UNKNOWN
License-File: LICENSE
